{"0":{"id":0,"name":"Бібліотека ім. Стіва Джобса","address":"Хрещатик","coordinates":{"latitude":50.450108,"longitude":30.524227},"books":[{"name":"Гаррі Поттер та Філософський Камінь","author":"Джоан Роулінг","coverUrl":"https://upload.wikimedia.org/wikipedia/en/thumb/6/6b/Harry_Potter_and_the_Philosopher%27s_Stone_Book_Cover.jpg/220px-Harry_Potter_and_the_Philosopher%27s_Stone_Book_Cover.jpg","isbn":"0-7475-3269-9","year":1997,"copies":[{"returnDate":1527797316723},{"returnDate":1527797316723}]},{"name":"Гаррі Поттер та В'язень Азкабану","author":"Джоан Роулінг","coverUrl":"https://upload.wikimedia.org/wikipedia/en/a/a0/Harry_Potter_and_the_Prisoner_of_Azkaban.jpg","isbn":"0-7475-4215-5","year":1999,"copies":[{"returnDate":1527797393823},{"returnDate":1527797393823},{"returnDate":1527797393823},{"returnDate":1527797393823},{"returnDate":1527797393823}]},{"name":"Гаррі Поттер та Таємна Кімната","author":"Джоан Роулінг","coverUrl":"https://upload.wikimedia.org/wikipedia/en/thumb/5/5c/Harry_Potter_and_the_Chamber_of_Secrets.jpg/220px-Harry_Potter_and_the_Chamber_of_Secrets.jpg","isbn":"0-7475-3849-2","year":1998,"copies":[{"returnDate":1527797731557},{"returnDate":1527797731557},{"returnDate":1527797731557},{"returnDate":1527797731557}]},{"name":"Гаррі Поттер і келих вогню","author":" Джоан Роулінг","coverUrl":"https://upload.wikimedia.org/wikipedia/en/c/c7/Harry_Potter_and_the_Goblet_of_Fire.jpg","isbn":"0-7475-4624-X","year":2000,"copies":[{"returnDate":1528020040937}]},{"name":"Гаррі Поттер і Орден Фенікса","author":"Джоан Роулінг","coverUrl":"https://upload.wikimedia.org/wikipedia/en/thumb/7/70/Harry_Potter_and_the_Order_of_the_Phoenix.jpg/220px-Harry_Potter_and_the_Order_of_the_Phoenix.jpg","isbn":"0-7475-5100-6","year":2003,"copies":[{"returnDate":1528020124332},{"returnDate":1528020124332},{"returnDate":1528020124332},{"returnDate":1528020124332},{"returnDate":1528020124332},{"returnDate":1528020124332}]},{"name":"Гаррі Поттер і напівкровний Принц","author":"Джоан Роулінг","coverUrl":"https://upload.wikimedia.org/wikipedia/en/f/f0/Harry_Potter_and_the_Half-Blood_Prince.jpg","isbn":"0-7475-8108-8","year":2005,"copies":[{"returnDate":1528020188244},{"returnDate":1528020188244},{"returnDate":1528020188244}]},{"name":"Гаррі Поттер і смертельні реліквії","author":"Джоан Роулінг","coverUrl":"https://upload.wikimedia.org/wikipedia/en/a/a9/Harry_Potter_and_the_Deathly_Hallows.jpg","isbn":"0-545-01022-5","year":2007,"copies":[{"returnDate":1528021516108},{"returnDate":1528020236549},{"returnDate":1528020236549}]},{"name":"Стів Джобс","author":"Волтер Айзексон","coverUrl":"https://upload.wikimedia.org/wikipedia/uk/thumb/e/e4/Steve_Jobs_by_Walter_Isaacson.jpg/200px-Steve_Jobs_by_Walter_Isaacson.jpg","isbn":"978-966-2665-02-4","year":2011,"copies":[{"returnDate":1528020329165},{"returnDate":1528020329165},{"returnDate":1528020329165},{"returnDate":1528020329165},{"returnDate":1528020329165}]}]},"1":{"id":"1","name":"Супер Крута бібліотека","address":"Центр Світу","coordinates":{"latitude":50.450108,"longitude":30.524227},"books":[{"name":"Володар перснів","author":"Дж.Р.Р. Толкін","coverUrl":"https://upload.wikimedia.org/wikipedia/uk/thumb/4/4f/Lotr_ukr.jpg/250px-Lotr_ukr.jpg","isbn":"0-395-08254-4","year":1955,"copies":[{"returnDate":1528020496275},{"returnDate":1528020496275},{"returnDate":1528020496275},{"returnDate":1528020496275},{"returnDate":1528020496275},{"returnDate":1528020496275}]},{"name":"Гобіт, або Туди і Звідти","author":"Дж.Р.Р. Толкін","coverUrl":"https://upload.wikimedia.org/wikipedia/uk/thumb/6/6b/Hobbit_Ukr.png/250px-Hobbit_Ukr.png","isbn":"530-101-224-Х","year":1937,"copies":[{"returnDate":1528020637883},{"returnDate":1528020671108},{"returnDate":1528020671108},{"returnDate":1528020671108},{"returnDate":1528020671108},{"returnDate":1528020671108},{"returnDate":1528020671108}]},{"name":"Сильмариліон","author":"Дж. Р.Р. Толкін","coverUrl":"https://upload.wikimedia.org/wikipedia/uk/5/51/Silmarillion_Ukr.png","isbn":"0-04-823139-8","year":1977,"copies":[{"returnDate":1528020715843},{"returnDate":1528020715843}]}]},"2":{"id":"2","name":"Бібліотека Сина Маминої Подруги","address":"Найкрутіше місце","coordinates":{"latitude":50.445960081872535,"longitude":30.575977887954878},"books":[{"name":"Гаррі Поттер та Філософський Камінь","author":"Джоан Роулінг","coverUrl":"https://upload.wikimedia.org/wikipedia/en/thumb/6/6b/Harry_Potter_and_the_Philosopher%27s_Stone_Book_Cover.jpg/220px-Harry_Potter_and_the_Philosopher%27s_Stone_Book_Cover.jpg","isbn":"0-7475-3269-9","year":1997,"copies":[{"returnDate":1527797316723},{"returnDate":1527797316723}]},{"name":"Гаррі Поттер та В'язень Азкабану","author":"Джоан Роулінг","coverUrl":"https://upload.wikimedia.org/wikipedia/en/a/a0/Harry_Potter_and_the_Prisoner_of_Azkaban.jpg","isbn":"0-7475-4215-5","year":1999,"copies":[{"returnDate":1527797393823},{"returnDate":1527797393823},{"returnDate":1527797393823},{"returnDate":1527797393823},{"returnDate":1527797393823}]},{"name":"Гаррі Поттер та Таємна Кімната","author":"Джоан Роулінг","coverUrl":"https://upload.wikimedia.org/wikipedia/en/thumb/5/5c/Harry_Potter_and_the_Chamber_of_Secrets.jpg/220px-Harry_Potter_and_the_Chamber_of_Secrets.jpg","isbn":"0-7475-3849-2","year":1998,"copies":[{"returnDate":1527797731557},{"returnDate":1527797731557},{"returnDate":1527797731557},{"returnDate":1527797731557}]},{"name":"Гаррі Поттер і келих вогню","author":" Джоан Роулінг","coverUrl":"https://upload.wikimedia.org/wikipedia/en/c/c7/Harry_Potter_and_the_Goblet_of_Fire.jpg","isbn":"0-7475-4624-X","year":2000,"copies":[{"returnDate":1528020040937}]},{"name":"Гаррі Поттер і Орден Фенікса","author":"Джоан Роулінг","coverUrl":"https://upload.wikimedia.org/wikipedia/en/thumb/7/70/Harry_Potter_and_the_Order_of_the_Phoenix.jpg/220px-Harry_Potter_and_the_Order_of_the_Phoenix.jpg","isbn":"0-7475-5100-6","year":2003,"copies":[{"returnDate":1528020124332},{"returnDate":1528020124332},{"returnDate":1528020124332},{"returnDate":1528020124332},{"returnDate":1528020124332},{"returnDate":1528020124332}]},{"name":"Гаррі Поттер і напівкровний Принц","author":"Джоан Роулінг","coverUrl":"https://upload.wikimedia.org/wikipedia/en/f/f0/Harry_Potter_and_the_Half-Blood_Prince.jpg","isbn":"0-7475-8108-8","year":2005,"copies":[{"returnDate":1528020188244},{"returnDate":1528020188244},{"returnDate":1528020188244}]},{"name":"Гаррі Поттер і смертельні реліквії","author":"Джоан Роулінг","coverUrl":"https://upload.wikimedia.org/wikipedia/en/a/a9/Harry_Potter_and_the_Deathly_Hallows.jpg","isbn":"0-545-01022-5","year":2007,"copies":[{"returnDate":1528020236549},{"returnDate":1528020236549},{"returnDate":1528020236549}]},{"name":"Стів Джобс","author":"Волтер Айзексон","coverUrl":"https://upload.wikimedia.org/wikipedia/uk/thumb/e/e4/Steve_Jobs_by_Walter_Isaacson.jpg/200px-Steve_Jobs_by_Walter_Isaacson.jpg","isbn":"978-966-2665-02-4","year":2011,"copies":[{"returnDate":1528020329165},{"returnDate":1528020329165},{"returnDate":1528020329165},{"returnDate":1528020329165},{"returnDate":1528020329165}]},{"name":"Володар перснів","author":"Дж.Р.Р. Толкін","coverUrl":"https://upload.wikimedia.org/wikipedia/uk/thumb/4/4f/Lotr_ukr.jpg/250px-Lotr_ukr.jpg","isbn":"0-395-08254-4","year":1955,"copies":[{"returnDate":1528020496275},{"returnDate":1528020496275},{"returnDate":1528020496275},{"returnDate":1528020496275},{"returnDate":1528020496275},{"returnDate":1528020496275}]},{"name":"Гобіт, або Туди і Звідти","author":"Дж.Р.Р. Толкін","coverUrl":"https://upload.wikimedia.org/wikipedia/uk/thumb/6/6b/Hobbit_Ukr.png/250px-Hobbit_Ukr.png","isbn":"530-101-224-Х","year":1937,"copies":[{"returnDate":1528020637883},{"returnDate":1528020671108},{"returnDate":1528020671108},{"returnDate":1528020671108},{"returnDate":1528020671108},{"returnDate":1528020671108},{"returnDate":1528020671108}]},{"name":"Сильмариліон","author":"Дж. Р.Р. Толкін","coverUrl":"https://upload.wikimedia.org/wikipedia/uk/5/51/Silmarillion_Ukr.png","isbn":"0-04-823139-8","year":1977,"copies":[{"returnDate":1528020715843},{"returnDate":1528020715843}]}]}}